cropmirror_counting/sahi_predict/__init__.py
cropmirror_counting/sahi_predict/sahi_counting_predict.py
cropmirror_counting/sahi_predict/setup.py
cropmirror_counting/sahi_predict/slice_counting_predict.py
cropmirror_counting/utils/__init__.py
cropmirror_counting/utils/download.py
cropmirror_counting/utils/imageProc.py
cropmirror_counting/utils/jpg2tiff.py
cropmirror_counting/utils/setup.py
cropmirror_counting/utils/tif2cog.py
cropmirror_counting/utils/tiffProc.py
cropmirror_counting/utils/wmct2wgs84.py
cropmirror_counting-0.0.3.dist-info/METADATA
cropmirror_counting-0.0.3.dist-info/WHEEL
cropmirror_counting-0.0.3.dist-info/RECORD
