Metadata-Version: 2.3
Name: cropmirror-counting
Version: 0.0.3
Summary: 云稷识别算法库
License: MIT
Author: Long.liu
Requires-Python: >=3.10,<4
Classifier: Programming Language :: Python :: 3
Classifier: Operating System :: OS Independent
Classifier: License :: OSI Approved :: MIT License
Requires-Dist: GDAL
Requires-Dist: Pillow (>=11.2.1)
Requires-Dist: Shapely (>=2.1.0)
Requires-Dist: chardet (>=5.2.0)
Requires-Dist: fiona (>=1.10.1)
Requires-Dist: loguru (>=0.7.3)
Requires-Dist: matplotlib (>=3.10.1)
Requires-Dist: numpy (>=2.2.5)
Requires-Dist: rasterio
Requires-Dist: rtree (>=1.4.0)
Requires-Dist: sahi (>=0.11.22)
Requires-Dist: scipy (>=1.15.2)
Requires-Dist: setuptools (>=75.8.0)
Requires-Dist: tifffile
Requires-Dist: torch (>=2.7.0)
Requires-Dist: torchvision (>=0.22.0)
Requires-Dist: ultralytics (>=8.3.105)
Project-URL: Bug Tracker, https://github.com/cropmirror/counting/issues
Project-URL: Repository, https://github.com/cropmirror/counting
